{
    "join": "Forces the bot to join the same voice channel that you are in",
    "leave": "Forces the bot to leave the voice channel it is currently in",
    "pause": "Pauses the playback of the currently playing song",
    "play": "Starts playing the provided song in the current voice channel.",
    "queue": "Displays the current list of songs in the queue",
    "remove": "Removes the given song from the queue",
    "restart": "Restarts playback of the current song from the beginning",
    "shuffle": "Mixes up the order of songs currently in the queue",
    "skip": "Skips the current song, immediately starting whatever is next",
    "shutdown": "Forces the bot to disconnect from the server and shutdown",
    "move": "Forces the bot to move to your voice channel if its somewhere else"
}
